version_upper.py
version_upper-0.2.2.dist-info/LICENSE
version_upper-0.2.2.dist-info/METADATA
version_upper-0.2.2.dist-info/WHEEL
version_upper-0.2.2.dist-info/entry_points.txt
version_upper-0.2.2.dist-info/top_level.txt
version_upper-0.2.2.dist-info/RECORD
