Metadata-Version: 2.1
Name: version-upper
Version: 0.2.2
Summary: Bump version strings in your repo
Home-page: https://github.com/hkiang01/version_upper
Author: Harrison Kiang
Author-email: hkiang01@gmail.com
License: UNKNOWN
Platform: UNKNOWN
Classifier: Programming Language :: Python :: 3.8
Classifier: Intended Audience :: Developers
Classifier: Topic :: Software Development
Classifier: License :: OSI Approved :: MIT License
Classifier: Operating System :: OS Independent
Classifier: Natural Language :: English
Requires-Python: >=3.6
Requires-Dist: click (!=3.0,!=5.0,>=0.7)
Requires-Dist: pydantic (>=1.0b1)
